pfinsim/asset.py
pfinsim/common.py
pfinsim/job.py
pfinsim/mortgage.py
pfinsim/simulation.py
pfinsim/taxes.py
pfinsim/resources/__init__.py
pfinsim/resources/settings.yml
pfinsim-0.0.10.dist-info/METADATA
pfinsim-0.0.10.dist-info/WHEEL
pfinsim-0.0.10.dist-info/top_level.txt
pfinsim-0.0.10.dist-info/RECORD
