Metadata-Version: 2.1
Name: pfinsim
Version: 0.0.10
Summary: Personal finance simulation package
Home-page: https://github.com/xgerrmann/pfinsim
Author: Xander Gerrmann
Author-email: <xander@xgerrmann.com>
License: UNKNOWN
Keywords: python,simulation,finance,personal
Platform: UNKNOWN
Classifier: Development Status :: 3 - Alpha
Classifier: Programming Language :: Python :: 3
Requires-Python: >=3.7
Requires-Dist: PyYAML (>=5.3.1)
